matrix-ops-helper/__init__.py
matrix-ops-helper/operations.py
matrix_operations/__init__.py
matrix_operations/operations.py
matrix_ops_helper_yq/__init__.py
matrix_ops_helper_yq/operations.py
matrix_ops_helper_yq-1.0.0.dist-info/LICENSE
matrix_ops_helper_yq-1.0.0.dist-info/METADATA
matrix_ops_helper_yq-1.0.0.dist-info/WHEEL
matrix_ops_helper_yq-1.0.0.dist-info/entry_points.txt
matrix_ops_helper_yq-1.0.0.dist-info/top_level.txt
matrix_ops_helper_yq-1.0.0.dist-info/RECORD
